{
    "runtime": 0.17470741271972656, 
    "schedule": {
        "0": 0.0, 
        "1": 0.001, 
        "3": 0.001, 
        "5": 0.001, 
        "7": 29.67332054780561, 
        "9": 44.50898082170839, 
        "10": 49.50898082170839, 
        "11": 59.345641095611214, 
        "12": 64.34564109561121, 
        "13": 64.34664109561122, 
        "15": 74.18030136951403, 
        "16": 79.18030136951403, 
        "17": 94.18630136951404, 
        "19": 79.18330136951403, 
        "20": 84.18330136951403, 
        "21": 84.18430136951403, 
        "22": 89.18430136951403, 
        "23": 89.18530136951404, 
        "25": 118.85762191731965, 
        "26": 123.85762191731965, 
        "27": 123.85862191731965, 
        "28": 128.85862191731965, 
        "29": 128.85962191731966, 
        "31": 118.85762191731965, 
        "32": 123.85762191731965, 
        "33": 158.53194246512527, 
        "34": 163.53194246512527, 
        "35": 123.85862191731965, 
        "36": 123.85962191731966, 
        "37": 163.53294246512527, 
        "38": 163.53394246512528, 
        "39": 168.0126, 
        "40": 168.0126
    }, 
    "probability": 1.0, 
    "network": {
        "name": "drones_instance-67_network_1_deadline_14_corrsize_2", 
        "timepoints": [
            {
                "id": 0, 
                "label": "PLAN_START"
            }, 
            {
                "id": 1, 
                "label": "(move d0 l9 l0)_start"
            }, 
            {
                "id": 2, 
                "label": "(move d0 l9 l0)_end"
            }, 
            {
                "id": 3, 
                "label": "(move d1 l9 l6)_start"
            }, 
            {
                "id": 4, 
                "label": "(move d1 l9 l6)_end"
            }, 
            {
                "id": 5, 
                "label": "(move d2 l9 l5)_start"
            }, 
            {
                "id": 6, 
                "label": "(move d2 l9 l5)_end"
            }, 
            {
                "id": 7, 
                "label": "(move d1 l6 l7)_start"
            }, 
            {
                "id": 8, 
                "label": "(move d1 l6 l7)_end"
            }, 
            {
                "id": 9, 
                "label": "(pick-up d0 l0 m0)_start"
            }, 
            {
                "id": 10, 
                "label": "(pick-up d0 l0 m0)_end"
            }, 
            {
                "id": 11, 
                "label": "(pick-up d1 l7 m1)_start"
            }, 
            {
                "id": 12, 
                "label": "(pick-up d1 l7 m1)_end"
            }, 
            {
                "id": 13, 
                "label": "(move d1 l7 l0)_start"
            }, 
            {
                "id": 14, 
                "label": "(move d1 l7 l0)_end"
            }, 
            {
                "id": 15, 
                "label": "(recharge d2 l5)_start"
            }, 
            {
                "id": 16, 
                "label": "(recharge d2 l5)_end"
            }, 
            {
                "id": 17, 
                "label": "(move d2 l5 l3)_start"
            }, 
            {
                "id": 18, 
                "label": "(move d2 l5 l3)_end"
            }, 
            {
                "id": 19, 
                "label": "(drop-off d1 l0 m1)_start"
            }, 
            {
                "id": 20, 
                "label": "(drop-off d1 l0 m1)_end"
            }, 
            {
                "id": 21, 
                "label": "(pick-up d0 l0 m1)_start"
            }, 
            {
                "id": 22, 
                "label": "(pick-up d0 l0 m1)_end"
            }, 
            {
                "id": 23, 
                "label": "(move d0 l0 l3)_start"
            }, 
            {
                "id": 24, 
                "label": "(move d0 l0 l3)_end"
            }, 
            {
                "id": 25, 
                "label": "(drop-off d0 l3 m1)_start"
            }, 
            {
                "id": 26, 
                "label": "(drop-off d0 l3 m1)_end"
            }, 
            {
                "id": 27, 
                "label": "(pick-up d2 l3 m1)_start"
            }, 
            {
                "id": 28, 
                "label": "(pick-up d2 l3 m1)_end"
            }, 
            {
                "id": 29, 
                "label": "(move d2 l3 l1)_start"
            }, 
            {
                "id": 30, 
                "label": "(move d2 l3 l1)_end"
            }, 
            {
                "id": 31, 
                "label": "(drop-off d0 l3 m0)_start"
            }, 
            {
                "id": 32, 
                "label": "(drop-off d0 l3 m0)_end"
            }, 
            {
                "id": 33, 
                "label": "(drop-off d2 l1 m1)_start"
            }, 
            {
                "id": 34, 
                "label": "(drop-off d2 l1 m1)_end"
            }, 
            {
                "id": 35, 
                "label": "(complete-delivery m0 l3)_start"
            }, 
            {
                "id": 36, 
                "label": "(complete-delivery m0 l3)_end"
            }, 
            {
                "id": 37, 
                "label": "(complete-delivery m1 l1)_start"
            }, 
            {
                "id": 38, 
                "label": "(complete-delivery m1 l1)_end"
            }, 
            {
                "id": 39, 
                "label": "TIL: (not (noexpired m0))"
            }, 
            {
                "id": 40, 
                "label": "TIL: (not (noexpired m1))"
            }
        ], 
        "constraints": [
            {
                "source": 0, 
                "sink": 39, 
                "label": "TIL: (not (noexpired m0))", 
                "type": "stc", 
                "duration_bound": {
                    "lb": 168.0126, 
                    "ub": 168.0126
                }
            }, 
            {
                "source": 0, 
                "sink": 40, 
                "label": "TIL: (not (noexpired m1))", 
                "type": "stc", 
                "duration_bound": {
                    "lb": 168.0126, 
                    "ub": 168.0126
                }
            }, 
            {
                "source": 1, 
                "sink": 2, 
                "label": "(move d0 l9 l0)", 
                "type": "pstc", 
                "distribution": {
                    "mean": 24.12653957781871, 
                    "sd": 6.282350134093622
                }
            }, 
            {
                "source": 0, 
                "sink": 1, 
                "label": "Ordering Constraint between 0 and 1", 
                "type": "stc", 
                "duration_bound": {
                    "lb": 0.001, 
                    "ub": 1000000000.0
                }
            }, 
            {
                "source": 3, 
                "sink": 4, 
                "label": "(move d1 l9 l6)", 
                "type": "pstc", 
                "distribution": {
                    "mean": 16.08435971854581, 
                    "sd": 4.188233422729081
                }
            }, 
            {
                "source": 0, 
                "sink": 3, 
                "label": "Ordering Constraint between 0 and 3", 
                "type": "stc", 
                "duration_bound": {
                    "lb": 0.001, 
                    "ub": 1000000000.0
                }
            }, 
            {
                "source": 5, 
                "sink": 6, 
                "label": "(move d2 l9 l5)", 
                "type": "pstc", 
                "distribution": {
                    "mean": 40.21089929636452, 
                    "sd": 10.470583556822703
                }
            }, 
            {
                "source": 0, 
                "sink": 5, 
                "label": "Ordering Constraint between 0 and 5", 
                "type": "stc", 
                "duration_bound": {
                    "lb": 0.001, 
                    "ub": 1000000000.0
                }
            }, 
            {
                "source": 7, 
                "sink": 8, 
                "label": "(move d1 l6 l7)", 
                "type": "pstc", 
                "distribution": {
                    "mean": 16.08435971854581, 
                    "sd": 4.188233422729081
                }
            }, 
            {
                "source": 4, 
                "sink": 7, 
                "label": "Ordering Constraint between 4 and 7", 
                "type": "stc", 
                "duration_bound": {
                    "lb": 0.001, 
                    "ub": 1000000000.0
                }
            }, 
            {
                "source": 0, 
                "sink": 7, 
                "label": "Ordering Constraint between 0 and 7", 
                "type": "stc", 
                "duration_bound": {
                    "lb": 0.001, 
                    "ub": 1000000000.0
                }
            }, 
            {
                "source": 9, 
                "sink": 10, 
                "label": "(pick-up d0 l0 m0)", 
                "type": "stc", 
                "duration_bound": {
                    "lb": 5.0, 
                    "ub": 5.0
                }
            }, 
            {
                "source": 3, 
                "sink": 9, 
                "label": "Interference Constraint between 3 and 9", 
                "type": "stc", 
                "duration_bound": {
                    "lb": 0.0, 
                    "ub": 1000000000.0
                }
            }, 
            {
                "source": 2, 
                "sink": 9, 
                "label": "Ordering Constraint between 2 and 9", 
                "type": "stc", 
                "duration_bound": {
                    "lb": 0.001, 
                    "ub": 1000000000.0
                }
            }, 
            {
                "source": 0, 
                "sink": 9, 
                "label": "Ordering Constraint between 0 and 9", 
                "type": "stc", 
                "duration_bound": {
                    "lb": 0.001, 
                    "ub": 1000000000.0
                }
            }, 
            {
                "source": 11, 
                "sink": 12, 
                "label": "(pick-up d1 l7 m1)", 
                "type": "stc", 
                "duration_bound": {
                    "lb": 5.0, 
                    "ub": 5.0
                }
            }, 
            {
                "source": 5, 
                "sink": 11, 
                "label": "Interference Constraint between 5 and 11", 
                "type": "stc", 
                "duration_bound": {
                    "lb": 0.0, 
                    "ub": 1000000000.0
                }
            }, 
            {
                "source": 2, 
                "sink": 11, 
                "label": "Interference Constraint between 2 and 11", 
                "type": "stc", 
                "duration_bound": {
                    "lb": 0.0, 
                    "ub": 1000000000.0
                }
            }, 
            {
                "source": 8, 
                "sink": 11, 
                "label": "Ordering Constraint between 8 and 11", 
                "type": "stc", 
                "duration_bound": {
                    "lb": 0.001, 
                    "ub": 1000000000.0
                }
            }, 
            {
                "source": 0, 
                "sink": 11, 
                "label": "Ordering Constraint between 0 and 11", 
                "type": "stc", 
                "duration_bound": {
                    "lb": 0.001, 
                    "ub": 1000000000.0
                }
            }, 
            {
                "source": 13, 
                "sink": 14, 
                "label": "(move d1 l7 l0)", 
                "type": "pstc", 
                "distribution": {
                    "mean": 8.042179859272904, 
                    "sd": 2.0941167113645407
                }
            }, 
            {
                "source": 12, 
                "sink": 13, 
                "label": "Ordering Constraint between 12 and 13", 
                "type": "stc", 
                "duration_bound": {
                    "lb": 0.001, 
                    "ub": 1000000000.0
                }
            }, 
            {
                "source": 15, 
                "sink": 16, 
                "label": "(recharge d2 l5)", 
                "type": "stc", 
                "duration_bound": {
                    "lb": 5.0, 
                    "ub": 5.0
                }
            }, 
            {
                "source": 4, 
                "sink": 15, 
                "label": "Interference Constraint between 4 and 15", 
                "type": "stc", 
                "duration_bound": {
                    "lb": 0.0, 
                    "ub": 1000000000.0
                }
            }, 
            {
                "source": 6, 
                "sink": 15, 
                "label": "Ordering Constraint between 6 and 15", 
                "type": "stc", 
                "duration_bound": {
                    "lb": 0.001, 
                    "ub": 1000000000.0
                }
            }, 
            {
                "source": 0, 
                "sink": 15, 
                "label": "Ordering Constraint between 0 and 15", 
                "type": "stc", 
                "duration_bound": {
                    "lb": 0.001, 
                    "ub": 1000000000.0
                }
            }, 
            {
                "source": 17, 
                "sink": 18, 
                "label": "(move d2 l5 l3)", 
                "type": "pstc", 
                "distribution": {
                    "mean": 16.08435971854581, 
                    "sd": 4.188233422729081
                }
            }, 
            {
                "source": 16, 
                "sink": 17, 
                "label": "Ordering Constraint between 16 and 17", 
                "type": "stc", 
                "duration_bound": {
                    "lb": 0.001, 
                    "ub": 1000000000.0
                }
            }, 
            {
                "source": 19, 
                "sink": 20, 
                "label": "(drop-off d1 l0 m1)", 
                "type": "stc", 
                "duration_bound": {
                    "lb": 5.0, 
                    "ub": 5.0
                }
            }, 
            {
                "source": 5, 
                "sink": 19, 
                "label": "Interference Constraint between 5 and 19", 
                "type": "stc", 
                "duration_bound": {
                    "lb": 0.0, 
                    "ub": 1000000000.0
                }
            }, 
            {
                "source": 2, 
                "sink": 19, 
                "label": "Interference Constraint between 2 and 19", 
                "type": "stc", 
                "duration_bound": {
                    "lb": 0.0, 
                    "ub": 1000000000.0
                }
            }, 
            {
                "source": 14, 
                "sink": 19, 
                "label": "Ordering Constraint between 14 and 19", 
                "type": "stc", 
                "duration_bound": {
                    "lb": 0.001, 
                    "ub": 1000000000.0
                }
            }, 
            {
                "source": 0, 
                "sink": 19, 
                "label": "Ordering Constraint between 0 and 19", 
                "type": "stc", 
                "duration_bound": {
                    "lb": 0.001, 
                    "ub": 1000000000.0
                }
            }, 
            {
                "source": 21, 
                "sink": 22, 
                "label": "(pick-up d0 l0 m1)", 
                "type": "stc", 
                "duration_bound": {
                    "lb": 5.0, 
                    "ub": 5.0
                }
            }, 
            {
                "source": 3, 
                "sink": 21, 
                "label": "Interference Constraint between 3 and 21", 
                "type": "stc", 
                "duration_bound": {
                    "lb": 0.0, 
                    "ub": 1000000000.0
                }
            }, 
            {
                "source": 20, 
                "sink": 21, 
                "label": "Ordering Constraint between 20 and 21", 
                "type": "stc", 
                "duration_bound": {
                    "lb": 0.001, 
                    "ub": 1000000000.0
                }
            }, 
            {
                "source": 2, 
                "sink": 21, 
                "label": "Ordering Constraint between 2 and 21", 
                "type": "stc", 
                "duration_bound": {
                    "lb": 0.001, 
                    "ub": 1000000000.0
                }
            }, 
            {
                "source": 0, 
                "sink": 21, 
                "label": "Ordering Constraint between 0 and 21", 
                "type": "stc", 
                "duration_bound": {
                    "lb": 0.001, 
                    "ub": 1000000000.0
                }
            }, 
            {
                "source": 9, 
                "sink": 22, 
                "label": "Interference Constraint between 9 and 22", 
                "type": "stc", 
                "duration_bound": {
                    "lb": 0.001, 
                    "ub": 1000000000.0
                }
            }, 
            {
                "source": 23, 
                "sink": 24, 
                "label": "(move d0 l0 l3)", 
                "type": "pstc", 
                "distribution": {
                    "mean": 16.08435971854581, 
                    "sd": 4.188233422729081
                }
            }, 
            {
                "source": 22, 
                "sink": 23, 
                "label": "Ordering Constraint between 22 and 23", 
                "type": "stc", 
                "duration_bound": {
                    "lb": 0.001, 
                    "ub": 1000000000.0
                }
            }, 
            {
                "source": 25, 
                "sink": 26, 
                "label": "(drop-off d0 l3 m1)", 
                "type": "stc", 
                "duration_bound": {
                    "lb": 5.0, 
                    "ub": 5.0
                }
            }, 
            {
                "source": 3, 
                "sink": 25, 
                "label": "Interference Constraint between 3 and 25", 
                "type": "stc", 
                "duration_bound": {
                    "lb": 0.0, 
                    "ub": 1000000000.0
                }
            }, 
            {
                "source": 24, 
                "sink": 25, 
                "label": "Ordering Constraint between 24 and 25", 
                "type": "stc", 
                "duration_bound": {
                    "lb": 0.001, 
                    "ub": 1000000000.0
                }
            }, 
            {
                "source": 0, 
                "sink": 25, 
                "label": "Ordering Constraint between 0 and 25", 
                "type": "stc", 
                "duration_bound": {
                    "lb": 0.001, 
                    "ub": 1000000000.0
                }
            }, 
            {
                "source": 27, 
                "sink": 28, 
                "label": "(pick-up d2 l3 m1)", 
                "type": "stc", 
                "duration_bound": {
                    "lb": 5.0, 
                    "ub": 5.0
                }
            }, 
            {
                "source": 4, 
                "sink": 27, 
                "label": "Interference Constraint between 4 and 27", 
                "type": "stc", 
                "duration_bound": {
                    "lb": 0.0, 
                    "ub": 1000000000.0
                }
            }, 
            {
                "source": 16, 
                "sink": 27, 
                "label": "Ordering Constraint between 16 and 27", 
                "type": "stc", 
                "duration_bound": {
                    "lb": 0.001, 
                    "ub": 1000000000.0
                }
            }, 
            {
                "source": 19, 
                "sink": 27, 
                "label": "Interference Constraint between 19 and 27", 
                "type": "stc", 
                "duration_bound": {
                    "lb": 0.0, 
                    "ub": 1000000000.0
                }
            }, 
            {
                "source": 26, 
                "sink": 27, 
                "label": "Ordering Constraint between 26 and 27", 
                "type": "stc", 
                "duration_bound": {
                    "lb": 0.001, 
                    "ub": 1000000000.0
                }
            }, 
            {
                "source": 18, 
                "sink": 27, 
                "label": "Ordering Constraint between 18 and 27", 
                "type": "stc", 
                "duration_bound": {
                    "lb": 0.001, 
                    "ub": 1000000000.0
                }
            }, 
            {
                "source": 29, 
                "sink": 30, 
                "label": "(move d2 l3 l1)", 
                "type": "pstc", 
                "distribution": {
                    "mean": 16.08435971854581, 
                    "sd": 4.188233422729081
                }
            }, 
            {
                "source": 28, 
                "sink": 29, 
                "label": "Ordering Constraint between 28 and 29", 
                "type": "stc", 
                "duration_bound": {
                    "lb": 0.001, 
                    "ub": 1000000000.0
                }
            }, 
            {
                "source": 0, 
                "sink": 29, 
                "label": "Ordering Constraint between 0 and 29", 
                "type": "stc", 
                "duration_bound": {
                    "lb": 0.001, 
                    "ub": 1000000000.0
                }
            }, 
            {
                "source": 31, 
                "sink": 32, 
                "label": "(drop-off d0 l3 m0)", 
                "type": "stc", 
                "duration_bound": {
                    "lb": 5.0, 
                    "ub": 5.0
                }
            }, 
            {
                "source": 3, 
                "sink": 31, 
                "label": "Interference Constraint between 3 and 31", 
                "type": "stc", 
                "duration_bound": {
                    "lb": 0.0, 
                    "ub": 1000000000.0
                }
            }, 
            {
                "source": 24, 
                "sink": 31, 
                "label": "Ordering Constraint between 24 and 31", 
                "type": "stc", 
                "duration_bound": {
                    "lb": 0.001, 
                    "ub": 1000000000.0
                }
            }, 
            {
                "source": 10, 
                "sink": 31, 
                "label": "Ordering Constraint between 10 and 31", 
                "type": "stc", 
                "duration_bound": {
                    "lb": 0.001, 
                    "ub": 1000000000.0
                }
            }, 
            {
                "source": 0, 
                "sink": 31, 
                "label": "Ordering Constraint between 0 and 31", 
                "type": "stc", 
                "duration_bound": {
                    "lb": 0.001, 
                    "ub": 1000000000.0
                }
            }, 
            {
                "source": 33, 
                "sink": 34, 
                "label": "(drop-off d2 l1 m1)", 
                "type": "stc", 
                "duration_bound": {
                    "lb": 5.0, 
                    "ub": 5.0
                }
            }, 
            {
                "source": 4, 
                "sink": 33, 
                "label": "Interference Constraint between 4 and 33", 
                "type": "stc", 
                "duration_bound": {
                    "lb": 0.0, 
                    "ub": 1000000000.0
                }
            }, 
            {
                "source": 16, 
                "sink": 33, 
                "label": "Ordering Constraint between 16 and 33", 
                "type": "stc", 
                "duration_bound": {
                    "lb": 0.001, 
                    "ub": 1000000000.0
                }
            }, 
            {
                "source": 19, 
                "sink": 33, 
                "label": "Interference Constraint between 19 and 33", 
                "type": "stc", 
                "duration_bound": {
                    "lb": 0.0, 
                    "ub": 1000000000.0
                }
            }, 
            {
                "source": 30, 
                "sink": 33, 
                "label": "Ordering Constraint between 30 and 33", 
                "type": "stc", 
                "duration_bound": {
                    "lb": 0.001, 
                    "ub": 1000000000.0
                }
            }, 
            {
                "source": 35, 
                "sink": 36, 
                "label": "(complete-delivery m0 l3)", 
                "type": "stc", 
                "duration_bound": {
                    "lb": 0.001, 
                    "ub": 0.001
                }
            }, 
            {
                "source": 32, 
                "sink": 35, 
                "label": "Ordering Constraint between 32 and 35", 
                "type": "stc", 
                "duration_bound": {
                    "lb": 0.001, 
                    "ub": 1000000000.0
                }
            }, 
            {
                "source": 0, 
                "sink": 35, 
                "label": "Ordering Constraint between 0 and 35", 
                "type": "stc", 
                "duration_bound": {
                    "lb": 0.001, 
                    "ub": 1000000000.0
                }
            }, 
            {
                "source": 37, 
                "sink": 38, 
                "label": "(complete-delivery m1 l1)", 
                "type": "stc", 
                "duration_bound": {
                    "lb": 0.001, 
                    "ub": 0.001
                }
            }, 
            {
                "source": 34, 
                "sink": 37, 
                "label": "Ordering Constraint between 34 and 37", 
                "type": "stc", 
                "duration_bound": {
                    "lb": 0.001, 
                    "ub": 1000000000.0
                }
            }, 
            {
                "source": 0, 
                "sink": 37, 
                "label": "Ordering Constraint between 0 and 37", 
                "type": "stc", 
                "duration_bound": {
                    "lb": 0.001, 
                    "ub": 1000000000.0
                }
            }, 
            {
                "source": 37, 
                "sink": 39, 
                "label": "Interference Constraint between 37 and 39", 
                "type": "stc", 
                "duration_bound": {
                    "lb": 0.0, 
                    "ub": 1000000000.0
                }
            }, 
            {
                "source": 38, 
                "sink": 39, 
                "label": "Interference Constraint between 38 and 39", 
                "type": "stc", 
                "duration_bound": {
                    "lb": 0.0, 
                    "ub": 1000000000.0
                }
            }, 
            {
                "source": 36, 
                "sink": 40, 
                "label": "Interference Constraint between 36 and 40", 
                "type": "stc", 
                "duration_bound": {
                    "lb": 0.0, 
                    "ub": 1000000000.0
                }
            }
        ], 
        "correlations": [
            {
                "constraints": [
                    {
                        "source": 1, 
                        "sink": 2, 
                        "label": "(move d0 l9 l0)", 
                        "type": "pstc", 
                        "distribution": {
                            "mean": 24.12653957781871, 
                            "sd": 6.282350134093622
                        }
                    }, 
                    {
                        "source": 23, 
                        "sink": 24, 
                        "label": "(move d0 l0 l3)", 
                        "type": "pstc", 
                        "distribution": {
                            "mean": 16.08435971854581, 
                            "sd": 4.188233422729081
                        }
                    }
                ], 
                "mean": [
                    24.12653957781871, 
                    16.08435971854581
                ], 
                "correlation": [
                    [
                        1.0, 
                        0.2558
                    ], 
                    [
                        0.2558, 
                        1.0
                    ]
                ]
            }, 
            {
                "constraints": [
                    {
                        "source": 3, 
                        "sink": 4, 
                        "label": "(move d1 l9 l6)", 
                        "type": "pstc", 
                        "distribution": {
                            "mean": 16.08435971854581, 
                            "sd": 4.188233422729081
                        }
                    }, 
                    {
                        "source": 7, 
                        "sink": 8, 
                        "label": "(move d1 l6 l7)", 
                        "type": "pstc", 
                        "distribution": {
                            "mean": 16.08435971854581, 
                            "sd": 4.188233422729081
                        }
                    }
                ], 
                "mean": [
                    16.08435971854581, 
                    16.08435971854581
                ], 
                "correlation": [
                    [
                        1.0, 
                        -0.919
                    ], 
                    [
                        -0.919, 
                        1.0
                    ]
                ]
            }, 
            {
                "constraints": [
                    {
                        "source": 5, 
                        "sink": 6, 
                        "label": "(move d2 l9 l5)", 
                        "type": "pstc", 
                        "distribution": {
                            "mean": 40.21089929636452, 
                            "sd": 10.470583556822703
                        }
                    }, 
                    {
                        "source": 17, 
                        "sink": 18, 
                        "label": "(move d2 l5 l3)", 
                        "type": "pstc", 
                        "distribution": {
                            "mean": 16.08435971854581, 
                            "sd": 4.188233422729081
                        }
                    }
                ], 
                "mean": [
                    40.21089929636452, 
                    16.08435971854581
                ], 
                "correlation": [
                    [
                        1.0, 
                        0.9692
                    ], 
                    [
                        0.9692, 
                        1.0
                    ]
                ]
            }
        ]
    }
}