{
    "runtime": 0.5678143501281738, 
    "schedule": {
        "0": 0.0, 
        "1": 0.001, 
        "3": 999999947.5387387, 
        "5": 999999947.5387387, 
        "7": 0.001, 
        "9": 60.269927032623286, 
        "10": 65.26992703262329, 
        "11": 65.27092703262329, 
        "13": 91.0028, 
        "14": 96.0028, 
        "15": 96.0038, 
        "16": 96.0048, 
        "17": 96.0048
    }, 
    "probability": 0.9406915596577666, 
    "network": {
        "name": "drones_instance-40_network_2_deadline_12_corrsize_2", 
        "timepoints": [
            {
                "id": 0, 
                "label": "PLAN_START"
            }, 
            {
                "id": 1, 
                "label": "(move d0 l7 l2)_start"
            }, 
            {
                "id": 2, 
                "label": "(move d0 l7 l2)_end"
            }, 
            {
                "id": 3, 
                "label": "(move d1 l7 l2)_start"
            }, 
            {
                "id": 4, 
                "label": "(move d1 l7 l2)_end"
            }, 
            {
                "id": 5, 
                "label": "(move d2 l7 l2)_start"
            }, 
            {
                "id": 6, 
                "label": "(move d2 l7 l2)_end"
            }, 
            {
                "id": 7, 
                "label": "(move d3 l7 l9)_start"
            }, 
            {
                "id": 8, 
                "label": "(move d3 l7 l9)_end"
            }, 
            {
                "id": 9, 
                "label": "(pick-up d3 l9 m0)_start"
            }, 
            {
                "id": 10, 
                "label": "(pick-up d3 l9 m0)_end"
            }, 
            {
                "id": 11, 
                "label": "(move d3 l9 l4)_start"
            }, 
            {
                "id": 12, 
                "label": "(move d3 l9 l4)_end"
            }, 
            {
                "id": 13, 
                "label": "(drop-off d3 l4 m0)_start"
            }, 
            {
                "id": 14, 
                "label": "(drop-off d3 l4 m0)_end"
            }, 
            {
                "id": 15, 
                "label": "(complete-delivery m0 l4)_start"
            }, 
            {
                "id": 16, 
                "label": "(complete-delivery m0 l4)_end"
            }, 
            {
                "id": 17, 
                "label": "TIL: (not (noexpired m0))"
            }
        ], 
        "constraints": [
            {
                "source": 0, 
                "sink": 17, 
                "label": "TIL: (not (noexpired m0))", 
                "type": "stc", 
                "duration_bound": {
                    "lb": 96.0048, 
                    "ub": 96.0048
                }
            }, 
            {
                "source": 1, 
                "sink": 2, 
                "label": "(move d0 l7 l2)", 
                "type": "pstc", 
                "distribution": {
                    "mean": 24.820258998803183, 
                    "sd": 6.910250570631294
                }
            }, 
            {
                "source": 0, 
                "sink": 1, 
                "label": "Ordering Constraint between 0 and 1", 
                "type": "stc", 
                "duration_bound": {
                    "lb": 0.001, 
                    "ub": 1000000000.0
                }
            }, 
            {
                "source": 3, 
                "sink": 4, 
                "label": "(move d1 l7 l2)", 
                "type": "pstc", 
                "distribution": {
                    "mean": 24.820258998803183, 
                    "sd": 6.910250570631294
                }
            }, 
            {
                "source": 0, 
                "sink": 3, 
                "label": "Ordering Constraint between 0 and 3", 
                "type": "stc", 
                "duration_bound": {
                    "lb": 0.001, 
                    "ub": 1000000000.0
                }
            }, 
            {
                "source": 5, 
                "sink": 6, 
                "label": "(move d2 l7 l2)", 
                "type": "pstc", 
                "distribution": {
                    "mean": 24.820258998803183, 
                    "sd": 6.910250570631294
                }
            }, 
            {
                "source": 0, 
                "sink": 5, 
                "label": "Ordering Constraint between 0 and 5", 
                "type": "stc", 
                "duration_bound": {
                    "lb": 0.001, 
                    "ub": 1000000000.0
                }
            }, 
            {
                "source": 7, 
                "sink": 8, 
                "label": "(move d3 l7 l9)", 
                "type": "pstc", 
                "distribution": {
                    "mean": 41.36709833133864, 
                    "sd": 11.51708428438549
                }
            }, 
            {
                "source": 0, 
                "sink": 7, 
                "label": "Ordering Constraint between 0 and 7", 
                "type": "stc", 
                "duration_bound": {
                    "lb": 0.001, 
                    "ub": 1000000000.0
                }
            }, 
            {
                "source": 9, 
                "sink": 10, 
                "label": "(pick-up d3 l9 m0)", 
                "type": "stc", 
                "duration_bound": {
                    "lb": 5.0, 
                    "ub": 5.0
                }
            }, 
            {
                "source": 2, 
                "sink": 9, 
                "label": "Interference Constraint between 2 and 9", 
                "type": "stc", 
                "duration_bound": {
                    "lb": 0.0, 
                    "ub": 1000000000.0
                }
            }, 
            {
                "source": 8, 
                "sink": 9, 
                "label": "Ordering Constraint between 8 and 9", 
                "type": "stc", 
                "duration_bound": {
                    "lb": 0.001, 
                    "ub": 1000000000.0
                }
            }, 
            {
                "source": 0, 
                "sink": 9, 
                "label": "Ordering Constraint between 0 and 9", 
                "type": "stc", 
                "duration_bound": {
                    "lb": 0.001, 
                    "ub": 1000000000.0
                }
            }, 
            {
                "source": 11, 
                "sink": 12, 
                "label": "(move d3 l9 l4)", 
                "type": "pstc", 
                "distribution": {
                    "mean": 16.546839332535455, 
                    "sd": 4.606833713754196
                }
            }, 
            {
                "source": 10, 
                "sink": 11, 
                "label": "Ordering Constraint between 10 and 11", 
                "type": "stc", 
                "duration_bound": {
                    "lb": 0.001, 
                    "ub": 1000000000.0
                }
            }, 
            {
                "source": 13, 
                "sink": 14, 
                "label": "(drop-off d3 l4 m0)", 
                "type": "stc", 
                "duration_bound": {
                    "lb": 5.0, 
                    "ub": 5.0
                }
            }, 
            {
                "source": 2, 
                "sink": 13, 
                "label": "Interference Constraint between 2 and 13", 
                "type": "stc", 
                "duration_bound": {
                    "lb": 0.0, 
                    "ub": 1000000000.0
                }
            }, 
            {
                "source": 12, 
                "sink": 13, 
                "label": "Ordering Constraint between 12 and 13", 
                "type": "stc", 
                "duration_bound": {
                    "lb": 0.001, 
                    "ub": 1000000000.0
                }
            }, 
            {
                "source": 0, 
                "sink": 13, 
                "label": "Ordering Constraint between 0 and 13", 
                "type": "stc", 
                "duration_bound": {
                    "lb": 0.001, 
                    "ub": 1000000000.0
                }
            }, 
            {
                "source": 15, 
                "sink": 16, 
                "label": "(complete-delivery m0 l4)", 
                "type": "stc", 
                "duration_bound": {
                    "lb": 0.001, 
                    "ub": 0.001
                }
            }, 
            {
                "source": 14, 
                "sink": 15, 
                "label": "Ordering Constraint between 14 and 15", 
                "type": "stc", 
                "duration_bound": {
                    "lb": 0.001, 
                    "ub": 1000000000.0
                }
            }, 
            {
                "source": 0, 
                "sink": 15, 
                "label": "Ordering Constraint between 0 and 15", 
                "type": "stc", 
                "duration_bound": {
                    "lb": 0.001, 
                    "ub": 1000000000.0
                }
            }, 
            {
                "source": 16, 
                "sink": 17, 
                "label": "Interference Constraint between 16 and 17", 
                "type": "stc", 
                "duration_bound": {
                    "lb": 0.0, 
                    "ub": 1000000000.0
                }
            }, 
            {
                "source": 0, 
                "sink": 4, 
                "label": "Deadline for Timepoint 4", 
                "type": "stc", 
                "duration_bound": {
                    "lb": 0, 
                    "ub": 1000000000.0
                }
            }, 
            {
                "source": 0, 
                "sink": 6, 
                "label": "Deadline for Timepoint 6", 
                "type": "stc", 
                "duration_bound": {
                    "lb": 0, 
                    "ub": 1000000000.0
                }
            }
        ], 
        "correlations": [
            {
                "constraints": [
                    {
                        "source": 7, 
                        "sink": 8, 
                        "label": "(move d3 l7 l9)", 
                        "type": "pstc", 
                        "distribution": {
                            "mean": 41.36709833133864, 
                            "sd": 11.51708428438549
                        }
                    }, 
                    {
                        "source": 11, 
                        "sink": 12, 
                        "label": "(move d3 l9 l4)", 
                        "type": "pstc", 
                        "distribution": {
                            "mean": 16.546839332535455, 
                            "sd": 4.606833713754196
                        }
                    }
                ], 
                "mean": [
                    41.36709833133864, 
                    16.546839332535455
                ], 
                "correlation": [
                    [
                        1.0, 
                        0.7894
                    ], 
                    [
                        0.7894, 
                        1.0
                    ]
                ]
            }
        ]
    }
}